coldcase/__init__.py
coldcase/main.py
ColdCase-0.1.5.dist-info/METADATA
ColdCase-0.1.5.dist-info/WHEEL
ColdCase-0.1.5.dist-info/entry_points.txt
ColdCase-0.1.5.dist-info/top_level.txt
ColdCase-0.1.5.dist-info/RECORD
