Metadata-Version: 2.1
Name: ColdCase
Version: 0.1.5
Summary: Various libraries
Home-page: https://github.com/AndrewJesse/ColdCase
Author: Andrew Marchese
Author-email: aj.marchese@outlook.com
Classifier: Programming Language :: Python :: 3
Classifier: License :: OSI Approved :: MIT License
Classifier: Operating System :: OS Independent
Requires-Python: >=3.6
Requires-Dist: pandas >=1.0.0
